brmodel/__init__.py
brmodel/cold_recommend.py
brmodel-0.2.0.dist-info/METADATA
brmodel-0.2.0.dist-info/WHEEL
brmodel-0.2.0.dist-info/entry_points.txt
brmodel-0.2.0.dist-info/RECORD
