Metadata-Version: 2.4
Name: brmodel
Version: 0.2.0
Summary: Add your description here
Author-email: peanut <17770030269@163.com>
Requires-Python: >=3.10
Requires-Dist: pandas>=2.2.3
Requires-Dist: scikit-learn>=1.6.1
